{
  "contacts": [
    {
      "firstName": "Alexey",
      "lastName": "Besedin",
      "phoneNumber": "7 (917) 531-5601",
      "favorite": false,
      "comment": "Лучший студент группы 171-333. Заслуживает 5 автоматом.",
      "id": 0
    },
    {
      "firstName": "Varvara",
      "lastName": "Shashkova",
      "phoneNumber": "0 (111) 000-0000",
      "favorite": true,
      "comment": "Будущий лучший студент на САПР (ещё не поступила), но ещё не вечер.",
      "id": 1
    }
  ],
  "sort": {
    "search": "",
    "option": 1
  }
}